osparc_control/__init__.py
osparc_control/core.py
osparc_control/errors.py
osparc_control/models.py
osparc_control/py.typed
osparc_control/transport/__init__.py
osparc_control/transport/base_transport.py
osparc_control/transport/in_memory.py
osparc_control/transport/zeromq.py
osparc_control-0.0.2.dist-info/LICENSE.md
osparc_control-0.0.2.dist-info/WHEEL
osparc_control-0.0.2.dist-info/METADATA
osparc_control-0.0.2.dist-info/RECORD
