Metadata-Version: 2.1
Name: osparc-control
Version: 0.0.2
Summary: Osparc Control
Home-page: https://github.com/ITISFoundation/osparc-control
License: MIT
Author: Andrei Neagu
Author-email: neagu@itis.swiss
Requires-Python: >=3.6.2,<4.0.0
Classifier: Development Status :: 4 - Beta
Classifier: License :: OSI Approved :: MIT License
Classifier: Programming Language :: Python :: 3
Classifier: Programming Language :: Python :: 3.10
Classifier: Programming Language :: Python :: 3.6
Classifier: Programming Language :: Python :: 3.7
Classifier: Programming Language :: Python :: 3.8
Classifier: Programming Language :: Python :: 3.9
Requires-Dist: click (>=8.0.1,<9.0.0)
Requires-Dist: pydantic (>=1.8.2)
Requires-Dist: pyzmq (>=14.0.0)
Requires-Dist: tenacity (>=8.0.1)
Requires-Dist: u-msgpack-python (>=2.7.1)
Project-URL: Changelog, https://github.com/ITISFoundation/osparc-control/releases
Project-URL: Documentation, https://itisfoundation.github.io/osparc-control/
Project-URL: Repository, https://github.com/ITISFoundation/osparc-control
